ccextender-1.28.data/scripts/ccextender
pkg/__init__.py
pkg/ccextender/__init__.py
pkg/ccextender/ccextender.py
pkg/ccextender/test_ccextender.py
pkg/ccextender/configs/ccextender.yaml
ccextender-1.28.dist-info/METADATA
ccextender-1.28.dist-info/WHEEL
ccextender-1.28.dist-info/top_level.txt
ccextender-1.28.dist-info/RECORD
