Metadata-Version: 2.1
Name: ccextender
Version: 1.28
Summary: Cookiecutter Extended
Home-page: https://github.com/aslape/ccextender
Author: aslape
Author-email: aslape@atlassian.com
License: UNKNOWN
Platform: UNKNOWN
Classifier: Programming Language :: Python :: 3
Classifier: License :: OSI Approved :: MIT License
Classifier: Operating System :: OS Independent
